dpy_toolbox/AutoHelp.py
dpy_toolbox/CustomContext.py
dpy_toolbox/EmojiReact.py
dpy_toolbox/__init__.py
dpy_toolbox/__main__.py
dpy_toolbox/bot.py
dpy_toolbox/permissions.py
dpy_toolbox/core/__init__.py
dpy_toolbox/core/default.py
dpy_toolbox/core/dpy_typing.py
dpy_toolbox/core/errors.py
dpy_toolbox/core/events.py
dpy_toolbox/core/filters.py
dpy_toolbox/core/translator.py
dpy_toolbox/helping/AutoHelp.py
dpy_toolbox/helping/NewHelp.py
dpy_toolbox/helping/__init__.py
dpy_toolbox/sink/__init__.py
dpy_toolbox/sink/base.py
dpy_toolbox/sink/encodings.py
dpy_toolbox/sink/gateway.py
dpy_toolbox/sink/injecter.py
dpy_toolbox/sink/old_gateway.py
dpy_toolbox/sink/opus.py
dpy_toolbox/sink/sink.py
dpy_toolbox/sink/voice_client.py
dpy_toolbox/translating/CommandTranslator.py
dpy_toolbox/translating/DictonaryTranslator.py
dpy_toolbox/translating/__init__.py
dpy_toolbox/ui/ButtonReact.py
dpy_toolbox/ui/Modal.py
dpy_toolbox/ui/Paginator.py
dpy_toolbox/ui/Settings.py
dpy_toolbox/ui/__init__.py
dpy_toolbox/ui/core.py
dpy_toolbox-0.0.1b31.dist-info/METADATA
dpy_toolbox-0.0.1b31.dist-info/WHEEL
dpy_toolbox-0.0.1b31.dist-info/top_level.txt
dpy_toolbox-0.0.1b31.dist-info/RECORD
