Metadata-Version: 2.1
Name: dpy-toolbox
Version: 0.0.1b31
Summary: Discord.py simplifier
Author: TheWever (Wever#3255)
Author-email: <nonarrator@gmail.com>
Project-URL: Github, https://github.com/TheWever/dpy-toolbox
Project-URL: Documentation, https://dpy-toolbox.rtfd.io/
Project-URL: Discord, https://discord.gg/rnEwUJ7Fhc
Keywords: discord.py,discord,utils,tools,toolbox
Classifier: Development Status :: 3 - Alpha
Classifier: Intended Audience :: Developers
Classifier: Programming Language :: Python :: 3
Classifier: Operating System :: Unix
Classifier: Operating System :: MacOS :: MacOS X
Classifier: Operating System :: Microsoft :: Windows
Requires-Dist: discord.py
Requires-Dist: PyNaCl
Requires-Dist: pydub
